<annotation>
	<folder>img</folder>
	<filename>01391.jpg</filename>
	<path>C:\Users\admin\Desktop\track_2\img\01391.jpg</path>
	<source>
		<database>Unknown</database>
	</source>
	<size>
		<width>416</width>
		<height>416</height>
		<depth>3</depth>
	</size>
	<segmented>0</segmented>
	<object>
		<name>Broccoli</name>
		<pose>Unspecified</pose>
		<truncated>0</truncated>
		<difficult>0</difficult>
		<bndbox>
			<xmin>61</xmin>
			<ymin>9</ymin>
			<xmax>90</xmax>
			<ymax>39</ymax>
		</bndbox>
	</object>
	<object>
		<name>Broccoli</name>
		<pose>Unspecified</pose>
		<truncated>0</truncated>
		<difficult>0</difficult>
		<bndbox>
			<xmin>111</xmin>
			<ymin>46</ymin>
			<xmax>141</xmax>
			<ymax>78</ymax>
		</bndbox>
	</object>
	<object>
		<name>Broccoli</name>
		<pose>Unspecified</pose>
		<truncated>0</truncated>
		<difficult>0</difficult>
		<bndbox>
			<xmin>54</xmin>
			<ymin>87</ymin>
			<xmax>79</xmax>
			<ymax>118</ymax>
		</bndbox>
	</object>
	<object>
		<name>Broccoli</name>
		<pose>Unspecified</pose>
		<truncated>0</truncated>
		<difficult>0</difficult>
		<bndbox>
			<xmin>105</xmin>
			<ymin>126</ymin>
			<xmax>147</xmax>
			<ymax>157</ymax>
		</bndbox>
	</object>
	<object>
		<name>Broccoli</name>
		<pose>Unspecified</pose>
		<truncated>0</truncated>
		<difficult>0</difficult>
		<bndbox>
			<xmin>50</xmin>
			<ymin>159</ymin>
			<xmax>81</xmax>
			<ymax>191</ymax>
		</bndbox>
	</object>
	<object>
		<name>Broccoli</name>
		<pose>Unspecified</pose>
		<truncated>0</truncated>
		<difficult>0</difficult>
		<bndbox>
			<xmin>110</xmin>
			<ymin>203</ymin>
			<xmax>141</xmax>
			<ymax>226</ymax>
		</bndbox>
	</object>
	<object>
		<name>Broccoli</name>
		<pose>Unspecified</pose>
		<truncated>0</truncated>
		<difficult>0</difficult>
		<bndbox>
			<xmin>42</xmin>
			<ymin>237</ymin>
			<xmax>78</xmax>
			<ymax>262</ymax>
		</bndbox>
	</object>
	<object>
		<name>Broccoli</name>
		<pose>Unspecified</pose>
		<truncated>0</truncated>
		<difficult>0</difficult>
		<bndbox>
			<xmin>98</xmin>
			<ymin>279</ymin>
			<xmax>130</xmax>
			<ymax>311</ymax>
		</bndbox>
	</object>
	<object>
		<name>Broccoli</name>
		<pose>Unspecified</pose>
		<truncated>0</truncated>
		<difficult>0</difficult>
		<bndbox>
			<xmin>29</xmin>
			<ymin>332</ymin>
			<xmax>64</xmax>
			<ymax>359</ymax>
		</bndbox>
	</object>
	<object>
		<name>Broccoli</name>
		<pose>Unspecified</pose>
		<truncated>0</truncated>
		<difficult>0</difficult>
		<bndbox>
			<xmin>89</xmin>
			<ymin>369</ymin>
			<xmax>127</xmax>
			<ymax>408</ymax>
		</bndbox>
	</object>
	<object>
		<name>Broccoli</name>
		<pose>Unspecified</pose>
		<truncated>0</truncated>
		<difficult>0</difficult>
		<bndbox>
			<xmin>281</xmin>
			<ymin>319</ymin>
			<xmax>314</xmax>
			<ymax>348</ymax>
		</bndbox>
	</object>
	<object>
		<name>Broccoli</name>
		<pose>Unspecified</pose>
		<truncated>0</truncated>
		<difficult>0</difficult>
		<bndbox>
			<xmin>337</xmin>
			<ymin>366</ymin>
			<xmax>366</xmax>
			<ymax>391</ymax>
		</bndbox>
	</object>
	<object>
		<name>Broccoli</name>
		<pose>Unspecified</pose>
		<truncated>0</truncated>
		<difficult>0</difficult>
		<bndbox>
			<xmin>348</xmin>
			<ymin>286</ymin>
			<xmax>375</xmax>
			<ymax>313</ymax>
		</bndbox>
	</object>
	<object>
		<name>Broccoli</name>
		<pose>Unspecified</pose>
		<truncated>0</truncated>
		<difficult>0</difficult>
		<bndbox>
			<xmin>278</xmin>
			<ymin>233</ymin>
			<xmax>316</xmax>
			<ymax>267</ymax>
		</bndbox>
	</object>
	<object>
		<name>Broccoli</name>
		<pose>Unspecified</pose>
		<truncated>0</truncated>
		<difficult>0</difficult>
		<bndbox>
			<xmin>352</xmin>
			<ymin>195</ymin>
			<xmax>391</xmax>
			<ymax>226</ymax>
		</bndbox>
	</object>
	<object>
		<name>Broccoli</name>
		<pose>Unspecified</pose>
		<truncated>0</truncated>
		<difficult>0</difficult>
		<bndbox>
			<xmin>297</xmin>
			<ymin>145</ymin>
			<xmax>331</xmax>
			<ymax>175</ymax>
		</bndbox>
	</object>
	<object>
		<name>Broccoli</name>
		<pose>Unspecified</pose>
		<truncated>0</truncated>
		<difficult>0</difficult>
		<bndbox>
			<xmin>366</xmin>
			<ymin>121</ymin>
			<xmax>390</xmax>
			<ymax>146</ymax>
		</bndbox>
	</object>
	<object>
		<name>Broccoli</name>
		<pose>Unspecified</pose>
		<truncated>0</truncated>
		<difficult>0</difficult>
		<bndbox>
			<xmin>295</xmin>
			<ymin>58</ymin>
			<xmax>330</xmax>
			<ymax>87</ymax>
		</bndbox>
	</object>
	<object>
		<name>Broccoli</name>
		<pose>Unspecified</pose>
		<truncated>0</truncated>
		<difficult>0</difficult>
		<bndbox>
			<xmin>367</xmin>
			<ymin>19</ymin>
			<xmax>398</xmax>
			<ymax>51</ymax>
		</bndbox>
	</object>
</annotation>
