<annotation>
	<folder>img</folder>
	<filename>01479.jpg</filename>
	<path>C:\Users\admin\Desktop\track_2\img\01479.jpg</path>
	<source>
		<database>Unknown</database>
	</source>
	<size>
		<width>416</width>
		<height>416</height>
		<depth>3</depth>
	</size>
	<segmented>0</segmented>
	<object>
		<name>Broccoli</name>
		<pose>Unspecified</pose>
		<truncated>1</truncated>
		<difficult>0</difficult>
		<bndbox>
			<xmin>80</xmin>
			<ymin>1</ymin>
			<xmax>108</xmax>
			<ymax>12</ymax>
		</bndbox>
	</object>
	<object>
		<name>Broccoli</name>
		<pose>Unspecified</pose>
		<truncated>0</truncated>
		<difficult>0</difficult>
		<bndbox>
			<xmin>66</xmin>
			<ymin>50</ymin>
			<xmax>104</xmax>
			<ymax>83</ymax>
		</bndbox>
	</object>
	<object>
		<name>Broccoli</name>
		<pose>Unspecified</pose>
		<truncated>0</truncated>
		<difficult>0</difficult>
		<bndbox>
			<xmin>152</xmin>
			<ymin>27</ymin>
			<xmax>174</xmax>
			<ymax>52</ymax>
		</bndbox>
	</object>
	<object>
		<name>Broccoli</name>
		<pose>Unspecified</pose>
		<truncated>0</truncated>
		<difficult>0</difficult>
		<bndbox>
			<xmin>134</xmin>
			<ymin>108</ymin>
			<xmax>164</xmax>
			<ymax>136</ymax>
		</bndbox>
	</object>
	<object>
		<name>Broccoli</name>
		<pose>Unspecified</pose>
		<truncated>0</truncated>
		<difficult>0</difficult>
		<bndbox>
			<xmin>56</xmin>
			<ymin>134</ymin>
			<xmax>94</xmax>
			<ymax>173</ymax>
		</bndbox>
	</object>
	<object>
		<name>Broccoli</name>
		<pose>Unspecified</pose>
		<truncated>0</truncated>
		<difficult>0</difficult>
		<bndbox>
			<xmin>42</xmin>
			<ymin>210</ymin>
			<xmax>74</xmax>
			<ymax>244</ymax>
		</bndbox>
	</object>
	<object>
		<name>Broccoli</name>
		<pose>Unspecified</pose>
		<truncated>0</truncated>
		<difficult>0</difficult>
		<bndbox>
			<xmin>126</xmin>
			<ymin>190</ymin>
			<xmax>154</xmax>
			<ymax>216</ymax>
		</bndbox>
	</object>
	<object>
		<name>Broccoli</name>
		<pose>Unspecified</pose>
		<truncated>0</truncated>
		<difficult>0</difficult>
		<bndbox>
			<xmin>33</xmin>
			<ymin>286</ymin>
			<xmax>68</xmax>
			<ymax>317</ymax>
		</bndbox>
	</object>
	<object>
		<name>Broccoli</name>
		<pose>Unspecified</pose>
		<truncated>0</truncated>
		<difficult>0</difficult>
		<bndbox>
			<xmin>112</xmin>
			<ymin>264</ymin>
			<xmax>136</xmax>
			<ymax>295</ymax>
		</bndbox>
	</object>
	<object>
		<name>Broccoli</name>
		<pose>Unspecified</pose>
		<truncated>0</truncated>
		<difficult>0</difficult>
		<bndbox>
			<xmin>109</xmin>
			<ymin>339</ymin>
			<xmax>141</xmax>
			<ymax>371</ymax>
		</bndbox>
	</object>
	<object>
		<name>Broccoli</name>
		<pose>Unspecified</pose>
		<truncated>0</truncated>
		<difficult>0</difficult>
		<bndbox>
			<xmin>32</xmin>
			<ymin>370</ymin>
			<xmax>63</xmax>
			<ymax>398</ymax>
		</bndbox>
	</object>
	<object>
		<name>Broccoli</name>
		<pose>Unspecified</pose>
		<truncated>0</truncated>
		<difficult>0</difficult>
		<bndbox>
			<xmin>304</xmin>
			<ymin>324</ymin>
			<xmax>333</xmax>
			<ymax>356</ymax>
		</bndbox>
	</object>
	<object>
		<name>Broccoli</name>
		<pose>Unspecified</pose>
		<truncated>0</truncated>
		<difficult>0</difficult>
		<bndbox>
			<xmin>356</xmin>
			<ymin>360</ymin>
			<xmax>396</xmax>
			<ymax>395</ymax>
		</bndbox>
	</object>
	<object>
		<name>Broccoli</name>
		<pose>Unspecified</pose>
		<truncated>0</truncated>
		<difficult>0</difficult>
		<bndbox>
			<xmin>366</xmin>
			<ymin>281</ymin>
			<xmax>406</xmax>
			<ymax>318</ymax>
		</bndbox>
	</object>
	<object>
		<name>Broccoli</name>
		<pose>Unspecified</pose>
		<truncated>0</truncated>
		<difficult>0</difficult>
		<bndbox>
			<xmin>315</xmin>
			<ymin>246</ymin>
			<xmax>342</xmax>
			<ymax>273</ymax>
		</bndbox>
	</object>
	<object>
		<name>Broccoli</name>
		<pose>Unspecified</pose>
		<truncated>0</truncated>
		<difficult>0</difficult>
		<bndbox>
			<xmin>382</xmin>
			<ymin>219</ymin>
			<xmax>399</xmax>
			<ymax>244</ymax>
		</bndbox>
	</object>
	<object>
		<name>Broccoli</name>
		<pose>Unspecified</pose>
		<truncated>0</truncated>
		<difficult>0</difficult>
		<bndbox>
			<xmin>332</xmin>
			<ymin>176</ymin>
			<xmax>355</xmax>
			<ymax>194</ymax>
		</bndbox>
	</object>
	<object>
		<name>Broccoli</name>
		<pose>Unspecified</pose>
		<truncated>1</truncated>
		<difficult>0</difficult>
		<bndbox>
			<xmin>392</xmin>
			<ymin>139</ymin>
			<xmax>416</xmax>
			<ymax>164</ymax>
		</bndbox>
	</object>
	<object>
		<name>Broccoli</name>
		<pose>Unspecified</pose>
		<truncated>1</truncated>
		<difficult>0</difficult>
		<bndbox>
			<xmin>391</xmin>
			<ymin>52</ymin>
			<xmax>416</xmax>
			<ymax>81</ymax>
		</bndbox>
	</object>
	<object>
		<name>Broccoli</name>
		<pose>Unspecified</pose>
		<truncated>0</truncated>
		<difficult>0</difficult>
		<bndbox>
			<xmin>336</xmin>
			<ymin>22</ymin>
			<xmax>361</xmax>
			<ymax>46</ymax>
		</bndbox>
	</object>
</annotation>
